setup.py
bbllaacckkwwoollff.egg-info/PKG-INFO
bbllaacckkwwoollff.egg-info/SOURCES.txt
bbllaacckkwwoollff.egg-info/dependency_links.txt
bbllaacckkwwoollff.egg-info/top_level.txt
service/__init__.py