Metadata-Version: 2.4
Name: bbllaacckkwwoollff
Version: 0.1
Summary: personal usage
Dynamic: summary
